sdk/__init__.py
sdk/_version.py
sdk/authentication.py
sdk/batch.py
sdk/client.py
sdk/endpoints.py
sdk/errors.py
sdk/job.py
sdk/py.typed
sdk/device/__init__.py
sdk/device/emulator_types.py
sdk/device/configuration/__init__.py
sdk/device/configuration/base_config.py
sdk/device/configuration/emu_free.py
sdk/device/configuration/emu_tn.py
sdk/utils/__init__.py
sdk/utils/jsend.py
sdk/utils/strenum.py
tests/__init__.py
tests/conftest.py
tests/test_batch.py
tests/test_client.py
tests/test_config.py
tests/test_device_specs.py
tests/test_doubles/__init__.py
tests/test_doubles/authentication.py
pasqal_sdk-0.2.0.dist-info/LICENSE
pasqal_sdk-0.2.0.dist-info/METADATA
pasqal_sdk-0.2.0.dist-info/WHEEL
pasqal_sdk-0.2.0.dist-info/top_level.txt
pasqal_sdk-0.2.0.dist-info/RECORD
