Metadata-Version: 2.1
Name: pasqal-sdk
Version: 0.2.0
Summary: Software development kit for Pasqal cloud platform.
Home-page: https://github.com/pasqal-io/cloud-sdk
Maintainer: Pasqal Cloud Services
Maintainer-email: pcs@pasqal.io
License: Apache 2.0
Classifier: Development Status :: 3 - Alpha
Classifier: Programming Language :: Python :: 3
Requires-Python: >=3.7
License-File: LICENSE
Requires-Dist: auth0-python (==3.23.1)
Requires-Dist: requests (==2.25.1)
Requires-Dist: requests-mock (==1.9.3)
Requires-Dist: pyjwt[crypto] (==2.5.0)
Requires-Dist: typing-extensions (==4.4.0) ; python_version == '3.7'
Provides-Extra: dev
Requires-Dist: flake8-import-order (==0.18.1) ; extra == 'dev'
Requires-Dist: mypy (==0.982) ; extra == 'dev'
Requires-Dist: black (==20.8b1) ; extra == 'dev'
Requires-Dist: flake8 (==3.9.0) ; extra == 'dev'
Requires-Dist: pytest (==6.2.5) ; extra == 'dev'
Requires-Dist: pytest-cov (==2.11.1) ; extra == 'dev'
Requires-Dist: types-requests (==2.25.1) ; extra == 'dev'
